{
  "name": "Labels - Empty",
  "id": "f5f4e7b3-97b7-4852-a334-834cb2dbce58",
  "url": "/",
  "dimensions": [
    "Desktop"
  ],
  "mocks": {},
  "browserState": {
    "localStorage": {
      "autoClosed": "{}",
      "url-https://github.com/codeyam/tabcommand": "{\"title\":\"codeyam/tabcommand — GitHub\",\"favicon\":\"\",\"processes\":{\"samples\":0}}",
      "labels": "{}",
      "activeTabs": "[{\"urlKey\":\"url-https://github.com/codeyam/tabcommand\",\"tabKey\":\"tab-401\",\"pinned\":false,\"tabCommandPinned\":false},{\"urlKey\":\"url-https://news.ycombinator.com\",\"tabKey\":\"tab-402\",\"pinned\":false,\"tabCommandPinned\":false}]",
      "url-https://news.ycombinator.com": "{\"title\":\"Hacker News\",\"favicon\":\"\",\"processes\":{\"samples\":10,\"network\":153600,\"cpu\":26000,\"privateMemory\":1596000000,\"jsMemoryAllocated\":1276800000,\"jsMemoryUsed\":957600000}}",
      "allUrls": "[\"url-https://github.com/codeyam/tabcommand\",\"url-https://news.ycombinator.com\"]"
    }
  },
  "scenarioType": "application",
  "pageFilePath": "src/lib/pages/App/App.jsx"
}